Workbook
Name City: 'Name range '!$F$3:$F$7
Name Days: 'Name range '!$E$16:$E$22
Name Designation: 'Name range '!$D$3:$D$7
Name Employee_Name: 'Name range '!$C$3:$C$7
Name Nums: 'Name range '!$F$16:$F$22
Name Salary: 'Name range '!$E$3:$E$7
Name Slicer_Amount: #N/A
Name Slicer_Date: #N/A
Name Slicer_Name: #N/A
Name Slicer_Region: #N/A

Sheet Data
A1: ID | B1: Full Name | C1: Email ID | D1: City | E1: Department | F1: Employee Code | I1: LEN() | J1: Upper() | K1: Lower() | L1: Mid() | M1: Left() | N1: Right() | O1: Proper() | P1: Concat() | Q1: & | R1: Text join | S1: Substitute() | T1: Replace()
A2: EMP101 | B2: Rahul Sharma | C2: rahul.sharma@gmail.com | D2: Mumbai | E2: Data Analytics | F2: DA-MUM-101 | I2: =LEN(B2) -> 12 | J2: =UPPER(B2) -> RAHUL SHARMA | K2: =LOWER(B2:B9) -> rahul sharma | L2: =MID(F2,4,3) -> MUM | M2: =LEFT(F2,2) -> DA | N2: =RIGHT(F2,3) -> 101 | O2: =PROPER(K2) -> Rahul Sharma | P2: =_xlfn.CONCAT(B2,",",E2,"-",D2) -> Rahul Sharma,Data Analytics-Mumbai | Q2: =B2&" -"&D2 -> Rahul Sharma -Mumbai | R2: =_xlfn.TEXTJOIN("|",TRUE,B2,D2,E2) -> Rahul Sharma|Mumbai|Data Analytics | S2: =SUBSTITUTE(F2,"-","|") -> DA|MUM|101 | T2: =REPLACE(F2,4,3,"TNA") -> DA-TNA-101
A3: EMP102 | B3: Priya Mehta | C3: priya.mehta@gmail.com | D3: Pune | E3: Human Resources | F3: HR-PUN-102 | I3: =LEN(B3) -> 11 | J3: =UPPER(B3) -> PRIYA MEHTA | K3: =LOWER(B3:B10) -> priya mehta | L3: =MID(F3,4,3) -> PUN | M3: =LEFT(F3,2) -> HR | N3: =RIGHT(F3,3) -> 102 | O3: =PROPER(K3) -> Priya Mehta | P3: =_xlfn.CONCAT(B3,",",E3,"-",D3) -> Priya Mehta,Human Resources-Pune | Q3: =B3&" -"&D3 -> Priya Mehta -Pune | R3: =_xlfn.TEXTJOIN("|",TRUE,B3,D3,E3) -> Priya Mehta|Pune|Human Resources | S3: =SUBSTITUTE(F3,"-","|") -> HR|PUN|102 | T3: =REPLACE(F3,4,3,"TNA") -> HR-TNA-102
A4: EMP103 | B4: Amit Kulkarni | C4: amit.kulkarni@gmail.com | D4: Thane | E4: Finance | F4: FN-THA-103 | I4: =LEN(B4) -> 13 | J4: =UPPER(B4) -> AMIT KULKARNI | K4: =LOWER(B4:B11) -> amit kulkarni | L4: =MID(F4,4,3) -> THA | M4: =LEFT(F4,2) -> FN | N4: =RIGHT(F4,3) -> 103 | O4: =PROPER(K4) -> Amit Kulkarni | P4: =_xlfn.CONCAT(B4,",",E4,"-",D4) -> Amit Kulkarni,Finance-Thane | Q4: =B4&" -"&D4 -> Amit Kulkarni -Thane | R4: =_xlfn.TEXTJOIN("|",TRUE,B4,D4,E4) -> Amit Kulkarni|Thane|Finance | S4: =SUBSTITUTE(F4,"-","|") -> FN|THA|103 | T4: =REPLACE(F4,4,3,"TNA") -> FN-TNA-103
A5: EMP104 | B5: Sneha Patil | C5: sneha.patil@gmail.com | D5: Mumbai | E5: Marketing | F5: MK-MUM-104 | I5: =LEN(B5) -> 11 | J5: =UPPER(B5) -> SNEHA PATIL | K5: =LOWER(B5:B12) -> sneha patil | L5: =MID(F5,4,3) -> MUM | M5: =LEFT(F5,2) -> MK | N5: =RIGHT(F5,3) -> 104 | O5: =PROPER(K5) -> Sneha Patil | P5: =_xlfn.CONCAT(B5,",",E5,"-",D5) -> Sneha Patil,Marketing-Mumbai | Q5: =B5&" -"&D5 -> Sneha Patil -Mumbai | R5: =_xlfn.TEXTJOIN("|",TRUE,B5,D5,E5) -> Sneha Patil|Mumbai|Marketing | S5: =SUBSTITUTE(F5,"-","|") -> MK|MUM|104 | T5: =REPLACE(F5,4,3,"TNA") -> MK-TNA-104
A6: EMP105 | B6: Rohan Desai | C6: rohan.desai@gmail.com | D6: Nashik | E6: Data Analytics | F6: DA-NAS-105 | I6: =LEN(B6) -> 11 | J6: =UPPER(B6) -> ROHAN DESAI | K6: =LOWER(B6:B13) -> rohan desai | L6: =MID(F6,4,3) -> NAS | M6: =LEFT(F6,2) -> DA | N6: =RIGHT(F6,3) -> 105 | O6: =PROPER(K6) -> Rohan Desai | P6: =_xlfn.CONCAT(B6,",",E6,"-",D6) -> Rohan Desai,Data Analytics-Nashik | Q6: =B6&" -"&D6 -> Rohan Desai -Nashik | R6: =_xlfn.TEXTJOIN("|",TRUE,B6,D6,E6) -> Rohan Desai|Nashik|Data Analytics | S6: =SUBSTITUTE(F6,"-","|") -> DA|NAS|105 | T6: =REPLACE(F6,4,3,"TNA") -> DA-TNA-105
A7: EMP106 | B7: Neha Joshi | C7: neha.joshi@gmail.com | D7: Pune | E7: Operations | F7: OP-PUN-106 | I7: =LEN(B7) -> 10 | J7: =UPPER(B7) -> NEHA JOSHI | K7: =LOWER(B7:B14) -> neha joshi | L7: =MID(F7,4,3) -> PUN | M7: =LEFT(F7,2) -> OP | N7: =RIGHT(F7,3) -> 106 | O7: =PROPER(K7) -> Neha Joshi | P7: =_xlfn.CONCAT(B7,",",E7,"-",D7) -> Neha Joshi,Operations-Pune | Q7: =B7&" -"&D7 -> Neha Joshi -Pune | R7: =_xlfn.TEXTJOIN("|",TRUE,B7,D7,E7) -> Neha Joshi|Pune|Operations | S7: =SUBSTITUTE(F7,"-","|") -> OP|PUN|106 | T7: =REPLACE(F7,4,3,"TNA") -> OP-TNA-106
A8: EMP107 | B8: Karan Shah | C8: karan.shah@gmail.com | D8: Thane | E8: Finance | F8: FN-THA-107 | I8: =LEN(B8) -> 10 | J8: =UPPER(B8) -> KARAN SHAH | K8: =LOWER(B8:B15) -> karan shah | L8: =MID(F8,4,3) -> THA | M8: =LEFT(F8,2) -> FN | N8: =RIGHT(F8,3) -> 107 | O8: =PROPER(K8) -> Karan Shah | P8: =_xlfn.CONCAT(B8,",",E8,"-",D8) -> Karan Shah,Finance-Thane | Q8: =B8&" -"&D8 -> Karan Shah -Thane | R8: =_xlfn.TEXTJOIN("|",TRUE,B8,D8,E8) -> Karan Shah|Thane|Finance | S8: =SUBSTITUTE(F8,"-","|") -> FN|THA|107 | T8: =REPLACE(F8,4,3,"TNA") -> FN-TNA-107
A9: EMP108 | B9: Anjali Rao | C9: anjali.rao@gmail.com | D9: Mumbai | E9: Human Resources | F9: HR-MUM-108 | I9: =LEN(B9) -> 10 | J9: =UPPER(B9) -> ANJALI RAO | K9: =LOWER(B9:B16) -> anjali rao | L9: =MID(F9,4,3) -> MUM | M9: =LEFT(F9,2) -> HR | N9: =RIGHT(F9,3) -> 108 | O9: =PROPER(K9) -> Anjali Rao | P9: =_xlfn.CONCAT(B9,",",E9,"-",D9) -> Anjali Rao,Human Resources-Mumbai | Q9: =B9&" -"&D9 -> Anjali Rao -Mumbai | R9: =_xlfn.TEXTJOIN("|",TRUE,B9,D9,E9) -> Anjali Rao|Mumbai|Human Resources | S9: =SUBSTITUTE(F9,"-","|") -> HR|MUM|108 | T9: =REPLACE(F9,4,3,"TNA") -> HR-TNA-108
O10: =PROPER(K10)
I12: Find() | J12: Search() | K12: Trim()
F13: AabbbBbbb | I13: =FIND("B",F13) -> 6 | J13: =SEARCH("b",F13) -> 3 | K13: =TRIM(F15) -> Good Morning
F14: AabbbBbbb | I14: =FIND("B",F14) -> 6 | J14: =SEARCH("b",F14) -> 3
F15: Good Morning

Sheet String questions
B2: 1 | C2: len() | D2: Find the number of characters in the employee's full name.
B3: 2 | C3: upper() | D3: Convert the department name to uppercase.
B4: 3 | C4: lower() | D4: Convert email address into lower case
B5: 4 | C5: proper() | D5: Convert names into proper case.
B6: 5 | C6: left() | D6: Extract the first 3 characters from the Employee Code.
B7: 6 | C7: right() | D7: Extract the last 3 digits of the Employee Code.
B8: 7 | C8: mid() | D8: Extract the city code
B9: 8 | C9: concat() | D9: Create a new Employee Description.
B10: 9 | C10: textjoin() | D10: Rahul Sharma | Mumbai | Data Analytics
B11: 10 | C11: Substitute() | D11: Replace - with / in the employee id's | F11: Replaces specific text
B12: 11 | C12: replace() | D12: Replace a specific portion of text based on position- MUM with THA | F12: Replaces based on position
B13: 12 | C13: trim()
B14: 13 | C14: find() | D14: find the position of @ in the email ID
B15: 14 | C15: search()

Sheet Date Functions
H2: Today
H3: Day
H4: Month
H5: Year
H7: Date Function
H11: First day of the current month
H12: First day of the previous month
H14: Last day of the current month
H15: Last day of the previous month
H17: No. of days between
H18: Years between
H20: Now
... H28: EDATE
H30: START DATE | I30: EOMONTH | J30: EDATE

Sheet Formula Referencing
A1: Invoice No. | B1: Product | C1: Quantity | D1: Price/Unit | E1: Discount % | F1: Gross Amount | G1: Discount Amount | H1: Net Amount | I1: GST | J1: Final Amount
A2: INV101 | B2: Laptop | C2: 3 | D2: 55000 | E2: 0.05 | F2: =C2*D2 -> 165000 | G2: =F2*E2 -> 8250 | H2: =F2-G2 -> 156750 | I2: =H2*$M$2 -> 28215 | J2: =H2+I2 -> 184965 | M2: 0.18
A3: INV102 | B3: Monitor | C3: 5 | D3: 18000 | E3: 0.08 | F3: =C3*D3 -> 90000 | G3: =F3*E3 -> 7200 | H3: =F3-G3 -> 82800 | I3: =H3*$M$2 -> 14904 | J3: =H3+I3 -> 97704
A4: INV103 | B4: Keyboard | C4: 10 | D4: 2500 | E4: 0.05 | F4: =C4*D4 -> 25000 | G4: =F4*E4 -> 1250 | H4: =F4-G4 -> 23750 | I4: =H4*$M$2 -> 4275 | J4: =H4+I4 -> 28025
A5: INV104 | B5: Mouse | C5: 15 | D5: 1200 | E5: 0.1 | F5: =C5*D5 -> 18000 | G5: =F5*E5 -> 1800 | H5: =F5-G5 -> 16200 | I5: =H5*$M$2 -> 2916 | J5: =H5+I5 -> 19116
A6: INV105 | B6: Laptop | C6: 2 | D6: 55000 | E6: 0.07 | F6: =C6*D6 -> 110000 | G6: =F6*E6 -> 7700 | H6: =F6-G6 -> 102300 | I6: =H6*$M$2 -> 18414 | J6: =H6+I6 -> 120714
A7: INV106 | B7: Monitor | C7: 7 | D7: 18000 | E7: 0.05 | F7: =C7*D7 -> 126000 | G7: =F7*E7 -> 6300 | H7: =F7-G7 -> 119700 | I7: =H7*$M$2 -> 21546 | J7: =H7+I7 -> 141246

Sheet FR-1
F2: Absolute Reference | G2: Relative Reference | M2: Mixed Reference
B4: Region | C4: Product | D4: Quantity | E4: Price | F4: Total Sales | G4: Total Sales with GST | M4: Discount Rates
B5: Arizona | C5: Mouse | D5: 5 | E5: 75 | F5: =D5*E5 -> 375 | G5: =F5*$K$6 -> 37.5 | M5: 0.1 | N5: 0.2 | O5: 0.3
B6: Texas | C6: Keyboard | D6: 10 | E6: 85 | F6: =D6*E6 -> 850 | G6: =F6*$K$6 -> 85 | J6: GST | K6: 0.1 | M6: =$F5*M$5 -> 37.5 | N6: =$F5*N$5 -> 75 | O6: =$F5*O$5 -> 112.5
B7: Florida | C7: Monitor | D7: 20 | E7: 90 | F7: =D7*E7 -> 1800 | G7: =F7*$K$6 -> 180 | M7: =$F6*M$5 -> 85 | N7: =$F6*N$5 -> 170 | O7: =$F6*O$5 -> 255
B8: Ohio | C8: HeadPhones | D8: 15 | E8: 45 | F8: =D8*E8 -> 675 | G8: =F8*$K$6 -> 67.5 | M8: =$F7*M$5 -> 180 | N8: =$F7*N$5 -> 360 | O8: =$F7*O$5 -> 540
B9: Alabama | C9: Monitor | D9: 18 | E9: 90 | F9: =D9*E9 -> 1620 | G9: =F9*$K$6 -> 162 | M9: =$F8*M$5 -> 67.5 | N9: =$F8*N$5 -> 135 | O9: =$F8*O$5 -> 202.5
B10: Nevada | C10: Monitor | D10: 8 | E10: 90 | F10: =D10*E10 -> 720 | G10: =F10*$K$6 -> 72 | M10: =$F9*M$5 -> 162 | N10: =$F9*N$5 -> 324 | O10: =$F9*O$5 -> 486
B11: Minnesota | C11: Mobile | D11: 9 | E11: 100 | F11: =D11*E11 -> 900 | G11: =F11*$K$6 -> 90 | M11: =$F10*M$5 -> 72 | N11: =$F10*N$5 -> 144 | O11: =$F10*O$5 -> 216
B12: Montana | C12: Keyboard | D12: 7 | E12: 85 | F12: =D12*E12 -> 595 | G12: =F12*$K$6 -> 59.5 | M12: =$F11*M$5 -> 90 | N12: =$F11*N$5 -> 180 | O12: =$F11*O$5 -> 270
M13: =$F12*M$5 -> 59.5 | N13: =$F12*N$5 -> 119 | O13: =$F12*O$5 -> 178.5

Sheet May
B7: Region | C7: sales
B8: E | C8: 100
B9: W | C9: 200
B10: N | C10: 300
B11: S | C11: 400

Sheet June
G2: Region | H2: sales
G3: E | H3: 800
G4: W | H4: 900
G5: N | H5: 1000
G6: S | H6: 500

Sheet Sheet1

Sheet july 
G2: Region | H2: sales
G3: E | H3: 400
G4: W | H4: 500
G5: N | H5: 700
G6: S | H6: 100

Sheet Multiple reference 
H3: =SUM('May:july '!H3) -> 1200
H5: Region | J5: sales
I6: String_Date_Formula_Ref | J6: ='july '!$H$3 -> 400
I7: String_Date_Formula_Ref | J7: =June!$H$3 -> 800
I8: String_Date_Formula_Ref | J8: =May!$C$8 -> 100
H9: E | J9: =SUM(J6:J8) -> 1300
I10: String_Date_Formula_Ref | J10: ='july '!$H$4 -> 500
I11: String_Date_Formula_Ref | J11: =June!$H$4 -> 900
I12: String_Date_Formula_Ref | J12: =May!$C$9 -> 200
H13: W | J13: =SUM(J10:J12) -> 1600
I14: String_Date_Formula_Ref | J14: ='july '!$H$5 -> 700
I15: String_Date_Formula_Ref | J15: =June!$H$5 -> 1000
I16: String_Date_Formula_Ref | J16: =May!$C$10 -> 300
H17: N | J17: =SUM(J14:J16) -> 2000
I18: String_Date_Formula_Ref | J18: ='july '!$H$6 -> 100
I19: String_Date_Formula_Ref | J19: =June!$H$6 -> 500
I20: String_Date_Formula_Ref | J20: =May!$C$11 -> 400
H21: S | J21: =SUM(J18:J20) -> 1000

Sheet  May1
C2: Q1 | D2: Q2 | E2: Q2 | F2: Q4
B3: Tea | C3: 500 | D3: 1500 | E3: 2000 | F3: 2354
B4: Coffee | C4: 7584 | D4: 4572 | E4: 4574 | F4: 4121
B5: Milk | C5: 5784 | D5: 9457 | E5: 4247 | F5: 8451

Sheet June 1
C2: Q1 | D2: Q2 | E2: Q2 | F2: Q4
B3: Tea | C3: 5784 | D3: 8945 | E3: 7421 | F3: 6541
B4: Coffee | C4: 3254 | D4: 5647 | E4: 4517 | F4: 4257
B5: Milk | C5: 7584 | D5: 2223 | E5: 2547 | F5: 4581

Sheet July 2
C2: Q1 | D2: Q2 | E2: Q2 | F2: Q4
B3: Tea | C3: 4574 | D3: 2545 | E3: 6542 | F3: 2152
B4: Coffee | C4: 4578 | D4: 3251 | E4: 4565 | F4: 6541
B5: Milk | C5: 5842 | D5: 7894 | E5: 6541 | F5: 5241

Sheet  Consolidation 1
E5: Sum
F6: Q1 | G6: Q2 | H6: Q4
E7: Tea | F7: 10858 | G7: 28953 | H7: 11047
E8: Coffee | F8: 15416 | G8: 27126 | H8: 14919
E9: Milk | F9: 19210 | G9: 32909 | H9: 18273

Sheet Name range 
C2: Employee Name | D2: Designation | E2: Salary | F2: City
C3: Riya | D3: Supevisor | E3: 3000 | F3: Thane
C4: Nita | D4: Manager | E4: 10000 | F4: Mumbai
C5: Priya | D5: Assisstant | E5: 8000 | F5: Pune
C6: Anjali | D6: Accountant | E6: 7000 | F6: Kolkata
C7: Aditi | D7: Clerk | E7: 2500 | F7: Delhi
C15: Functions | D15: Named Ranges | E15: Text | F15: Numbers
C16: sum | D16: =SUM(Salary) -> 30500 | E16: Monday | F16: 10
C17: min | D17: =MIN(Salary) -> 2500 | E17: Tuesday | F17: 20
C18: max | D18: =MAX(Salary) -> 10000 | E18: Wednesday | F18: 30
C19: average | D19: =AVERAGE(Salary) -> 6100 | E19: Thursday | F19: 40
C20: count | D20: =COUNT(Employee_Name) -> 0 | E20: Friday | F20: 50
C21: counta | E21: Saturday | F21: 60
C22: countblank | E22: Sunday | F22: 70

Sheet Practise sheet 
F4: =SUM(Salary) -> 30500
F8: =AVERAGE(Salary) -> 6100
I9: =SUM(Nums) -> 280

Sheet Table in excel 
G6: Date | H6: Region | I6: Name | J6: Amount
G7: 2/14/2018 | H7: North | I7: John | J7: 500
G8: 2/15/2018 | H8: South | I8: Robert | J8: 650
G9: 2/16/2018 | H9: Northeast | I9: Michael | J9: 482
G10: 2/17/2018 | H10: East | I10: William | J10: 541
G11: 2/18/2018 | H11: West | I11: David | J11: 521
G12: 2/19/2018 | H12: Southeast | I12: Richard | J12: 5425
G13: 2/20/2018 | H13: West | I13: Joseph | J13: 857
G14: 2/21/2018 | H14: East | I14: Charles | J14: 741
G15: 2/22/2018 | H15: North | I15: Thomas | J15: 987
G16: 2/23/2018 | H16: South | I16: Harry | J16: 545
G17: 2/24/2018 | H17: West | I17: Jacob | J17: 635
G18: Total | J18: =SUBTOTAL(104,Practise_table[Amount]) -> 5425
